{
  "routes": [
    {
      "method": "GET",
      "path": "/angebotes",
      "handler": "angebote.find",
      "config": {
        "policies": []
      }
    },
    {
      "method": "GET",
      "path": "/angebotes/count",
      "handler": "angebote.count",
      "config": {
        "policies": []
      }
    },
    {
      "method": "GET",
      "path": "/angebotes/:id",
      "handler": "angebote.findOne",
      "config": {
        "policies": []
      }
    },
    {
      "method": "POST",
      "path": "/angebotes",
      "handler": "angebote.create",
      "config": {
        "policies": []
      }
    },
    {
      "method": "PUT",
      "path": "/angebotes/:id",
      "handler": "angebote.update",
      "config": {
        "policies": []
      }
    },
    {
      "method": "DELETE",
      "path": "/angebotes/:id",
      "handler": "angebote.delete",
      "config": {
        "policies": []
      }
    }
  ]
}
